{
  "Firstname": "Tên riêng",
  "Firstname can not be empty!": "Tên riêng không được để trống!",
  "Lastname": "Tên họ",
  "Lastname can not be empty!": "Tên họ không được để trống!",
  "Email": "Địa chỉ email",
  "Email has been taken!": "Địa chỉ email đã được đăng ký!",
  "Password": "Mật khẩu",
  "Password can not be empty or less than 6 characters!": "Mật khẩu không được để trống hoặc nhỏ hơn 6 ký tự!",
  "Address": "Địa chỉ nhà",
  "Address can not be empty!": "Địa chỉ nhà không được để trống!",
  "District": "Tên quận",
  "District can not be empty!": "Tên quận không được để trống!",
  "City": "Tên thành phố",
  "City can not be empty!": "Tên thành phố  không được để trống!"
}